{
    "110": {
        "x": 169,
        "y": 42
    },
    "111": {
        "x": 286,
        "y": 48
    },
    "112": {
        "x": 426,
        "y": 63
    },
    "113": {
        "x": 560,
        "y": 38
    },
    "114": {
        "x": 673,
        "y": 43
    },
    "115": {
        "x": 480,
        "y": 105
    },
    "117": {
        "x": 923,
        "y": 257
    },
    "118": {
        "x": 732,
        "y": 45
    },
    "119": {
        "x": 757,
        "y": 142
    },
    "120": {
        "x": 796,
        "y": 240
    },
    "121": {
        "x": 774,
        "y": 178
    },
    "122": {
        "x": 490,
        "y": 863
    },
    "123": {
        "x": 625,
        "y": 875
    },
    "124": {
        "x": 718,
        "y": 752
    },
    "125": {
        "x": 788,
        "y": 759
    },
    "126": {
        "x": 860,
        "y": 737
    },
    "127": {
        "x": 709,
        "y": 788
    },
    "128": {
        "x": 289,
        "y": 128
    },
    "129": {
        "x": 510,
        "y": 204
    },
    "130": {
        "x": 472,
        "y": 273
    },
    "131": {
        "x": 444,
        "y": 285
    },
    "132": {
        "x": 541,
        "y": 372
    },
    "133": {
        "x": 485,
        "y": 550
    },
    "134": {
        "x": 536,
        "y": 530
    },
    "135": {
        "x": 544,
        "y": 232
    },
    "136": {
        "x": 477,
        "y": 210
    },
    "137": {
        "x": 358,
        "y": 464
    },
    "138": {
        "x": 586,
        "y": 501
    },
    "139": {
        "x": 541,
        "y": 122
    },
    "140": {
        "x": 597,
        "y": 435
    },
    "10": {
        "x": 182,
        "y": 668
    },
    "11": {
        "x": 215,
        "y": 607
    },
    "12": {
        "x": 130,
        "y": 639
    },
    "13": {
        "x": 158,
        "y": 640
    },
    "14": {
        "x": 120,
        "y": 583
    },
    "15": {
        "x": 53,
        "y": 545
    },
    "16": {
        "x": 208,
        "y": 631
    },
    "17": {
        "x": 230,
        "y": 650
    },
    "18": {
        "x": 349,
        "y": 612
    },
    "19": {
        "x": 513,
        "y": 578
    },
    "1": {
        "x": 765,
        "y": 801
    },
    "20": {
        "x": 331,
        "y": 648
    },
    "21": {
        "x": 333,
        "y": 718
    },
    "22": {
        "x": 372,
        "y": 650
    },
    "23": {
        "x": 489,
        "y": 516
    },
    "24": {
        "x": 517,
        "y": 551
    },
    "25": {
        "x": 573,
        "y": 479
    },
    "26": {
        "x": 526,
        "y": 503
    },
    "27": {
        "x": 642,
        "y": 517
    },
    "28": {
        "x": 571,
        "y": 599
    },
    "29": {
        "x": 648,
        "y": 651
    },
    "2": {
        "x": 298,
        "y": 599
    },
    "30": {
        "x": 474,
        "y": 631
    },
    "31": {
        "x": 427,
        "y": 670
    },
    "32": {
        "x": 530,
        "y": 694
    },
    "33": {
        "x": 634,
        "y": 688
    },
    "34": {
        "x": 506,
        "y": 724
    },
    "35": {
        "x": 605,
        "y": 574
    },
    "36": {
        "x": 647,
        "y": 560
    },
    "37": {
        "x": 764,
        "y": 602
    },
    "38": {
        "x": 778,
        "y": 634
    },
    "39": {
        "x": 714,
        "y": 576
    },
    "3": {
        "x": 444,
        "y": 474
    },
    "40": {
        "x": 692,
        "y": 530
    },
    "41": {
        "x": 673,
        "y": 448
    },
    "42": {
        "x": 774,
        "y": 525
    },
    "43": {
        "x": 890,
        "y": 454
    },
    "44": {
        "x": 863,
        "y": 677
    },
    "45": {
        "x": 927,
        "y": 503
    },
    "46": {
        "x": 822,
        "y": 583
    },
    "47": {
        "x": 763,
        "y": 425
    },
    "48": {
        "x": 776,
        "y": 386
    },
    "4": {
        "x": 381,
        "y": 417
    },
    "50": {
        "x": 675,
        "y": 393
    },
    "51": {
        "x": 712,
        "y": 379
    },
    "52": {
        "x": 745,
        "y": 361
    },
    "53": {
        "x": 672,
        "y": 481
    },
    "54": {
        "x": 63,
        "y": 490
    },
    "55": {
        "x": 200,
        "y": 456
    },
    "56": {
        "x": 296,
        "y": 418
    },
    "57": {
        "x": 58,
        "y": 435
    },
    "58": {
        "x": 91,
        "y": 387
    },
    "59": {
        "x": 178,
        "y": 373
    },
    "5": {
        "x": 558,
        "y": 511
    },
    "60": {
        "x": 213,
        "y": 341
    },
    "61": {
        "x": 86,
        "y": 331
    },
    "62": {
        "x": 105,
        "y": 231
    },
    "63": {
        "x": 164,
        "y": 269
    },
    "64": {
        "x": 63,
        "y": 128
    },
    "65": {
        "x": 174,
        "y": 147
    },
    "66": {
        "x": 286,
        "y": 218
    },
    "67": {
        "x": 299,
        "y": 328
    },
    "68": {
        "x": 368,
        "y": 353
    },
    "69": {
        "x": 485,
        "y": 427
    },
    "6": {
        "x": 598,
        "y": 526
    },
    "70": {
        "x": 436,
        "y": 319
    },
    "71": {
        "x": 582,
        "y": 403
    },
    "72": {
        "x": 612,
        "y": 444
    },
    "74": {
        "x": 591,
        "y": 172
    },
    "75": {
        "x": 632,
        "y": 182
    },
    "76": {
        "x": 647,
        "y": 158
    },
    "77": {
        "x": 582,
        "y": 240
    },
    "78": {
        "x": 583,
        "y": 291
    },
    "7": {
        "x": 501,
        "y": 297
    },
    "80": {
        "x": 583,
        "y": 115
    },
    "81": {
        "x": 535,
        "y": 150
    },
    "82": {
        "x": 622,
        "y": 340
    },
    "83": {
        "x": 709,
        "y": 293
    },
    "85": {
        "x": 628,
        "y": 317
    },
    "86": {
        "x": 864,
        "y": 116
    },
    "87": {
        "x": 694,
        "y": 252
    },
    "88": {
        "x": 685,
        "y": 204
    },
    "89": {
        "x": 801,
        "y": 133
    },
    "8": {
        "x": 560,
        "y": 305
    },
    "90": {
        "x": 801,
        "y": 58
    },
    "91": {
        "x": 826,
        "y": 185
    },
    "92": {
        "x": 816,
        "y": 304
    },
    "93": {
        "x": 894,
        "y": 284
    },
    "94": {
        "x": 1002,
        "y": 280
    },
    "95": {
        "x": 709,
        "y": 280
    },
    "96": {
        "x": 878,
        "y": 133
    },
    "97": {
        "x": 883,
        "y": 63
    },
    "98": {
        "x": 1207,
        "y": 29
    },
    "9": {
        "x": 574,
        "y": 202
    },
    "a": {
        "x": 401,
        "y": 745
    },
    "b": {
        "x": 296,
        "y": 623
    },
    "c": {
        "x": 269,
        "y": 541
    },
    "d": {
        "x": 469,
        "y": 503
    },
    "e": {
        "x": 400,
        "y": 487
    },
    "f": {
        "x": 357,
        "y": 472
    },
    "g": {
        "x": 454,
        "y": 444
    },
    "h": {
        "x": 353,
        "y": 427
    },
    "j": {
        "x": 105,
        "y": 526
    },
    "k": {
        "x": 139,
        "y": 315
    },
    "l": {
        "x": 424,
        "y": 195
    },
    "m": {
        "x": 224,
        "y": 188
    },
    "n": {
        "x": 323,
        "y": 159
    },
    "p": {
        "x": 267,
        "y": 288
    },
    "q": {
        "x": 412,
        "y": 277
    },
    "r": {
        "x": 460,
        "y": 218
    },
    "s": {
        "x": 339,
        "y": 189
    },
    "u": {
        "x": 546,
        "y": 344
    },
    "v": {
        "x": 570,
        "y": 427
    },
    "w": {
        "x": 464,
        "y": 540
    },
    "x": {
        "x": 612,
        "y": 618
    },
    "y": {
        "x": 564,
        "y": 498
    },
    "z": {
        "x": 570,
        "y": 486
    }
}
